faceservice/__init__.py
faceservice/action.py
faceservice/be_happy.py
faceservice/cli.py
faceservice/config.py
faceservice/demo.py
faceservice/eye_bk.py
faceservice/faceservice.py
faceservice/web_demo_test.py
faceservice/lib/__init__.py
faceservice/lib/core/__init__.py
faceservice/lib/core/LK/__init__.py
faceservice/lib/core/LK/lk.py
faceservice/lib/core/api/__init__.py
faceservice/lib/core/api/face_detector.py
faceservice/lib/core/api/face_landmark.py
faceservice/lib/core/api/facer.py
faceservice/lib/core/beauty/__init__.py
faceservice/lib/core/beauty/thin.py
faceservice/lib/core/headpose/__init__.py
faceservice/lib/core/headpose/pose.py
faceservice/lib/logger/__init__.py
faceservice/lib/logger/logger.py
faceservice/lib/web/__init__.py
faceservice/lib/web/http.py
faceservice/lib/web/utils.py
faceservice/model/detector/saved_model.pb
faceservice/model/detector/variables/variables.data-00000-of-00002
faceservice/model/detector/variables/variables.data-00001-of-00002
faceservice/model/detector/variables/variables.index
faceservice/model/keypoints/saved_model.pb
faceservice/model/keypoints/variables/variables.data-00000-of-00002
faceservice/model/keypoints/variables/variables.data-00001-of-00002
faceservice/model/keypoints/variables/variables.index
faceservice-3.0.dist-info/AUTHORS.rst
faceservice-3.0.dist-info/LICENSE
faceservice-3.0.dist-info/METADATA
faceservice-3.0.dist-info/WHEEL
faceservice-3.0.dist-info/entry_points.txt
faceservice-3.0.dist-info/top_level.txt
faceservice-3.0.dist-info/RECORD
